trainloop_cli/__init__.py
trainloop_cli/__main__.py
trainloop_cli/commands/__init__.py
trainloop_cli/commands/add.py
trainloop_cli/commands/benchmark/README.md
trainloop_cli/commands/benchmark/__init__.py
trainloop_cli/commands/benchmark/command.py
trainloop_cli/commands/benchmark/constants.py
trainloop_cli/commands/benchmark/loaders.py
trainloop_cli/commands/benchmark/output.py
trainloop_cli/commands/benchmark/runner.py
trainloop_cli/commands/benchmark/storage.py
trainloop_cli/commands/benchmark/types.py
trainloop_cli/commands/benchmark/validators.py
trainloop_cli/commands/eval.py
trainloop_cli/commands/init.py
trainloop_cli/commands/studio.py
trainloop_cli/commands/utils.py
trainloop_cli/eval_core/__init__.py
trainloop_cli/eval_core/_trace_helpers.py
trainloop_cli/eval_core/benchmark_schema.md
trainloop_cli/eval_core/helpers.py
trainloop_cli/eval_core/judge.py
trainloop_cli/eval_core/runner.py
trainloop_cli/eval_core/types.py
trainloop_cli/scaffold/trainloop/.env.example
trainloop_cli/scaffold/trainloop/.gitignore
trainloop_cli/scaffold/trainloop/README.md
trainloop_cli/scaffold/trainloop/eval/__init__.py
trainloop_cli/scaffold/trainloop/eval/metrics/__init__.py
trainloop_cli/scaffold/trainloop/eval/metrics/always_pass.py
trainloop_cli/scaffold/trainloop/eval/metrics/benchmark_response_quality.py
trainloop_cli/scaffold/trainloop/eval/metrics/is_helpful.py
trainloop_cli/scaffold/trainloop/eval/suites/__init__.py
trainloop_cli/scaffold/trainloop/eval/suites/always_passes.py
trainloop_cli/scaffold/trainloop/eval/suites/is_helpful.py
trainloop_cli/scaffold/trainloop/trainloop.config.yaml
trainloop_cli-0.8.0.dist-info/METADATA
trainloop_cli-0.8.0.dist-info/WHEEL
trainloop_cli-0.8.0.dist-info/entry_points.txt
trainloop_cli-0.8.0.dist-info/RECORD
