Metadata-Version: 2.3
Name: trainloop-cli
Version: 0.8.0
Summary: TrainLoop command-line interface
Author: Mason Pierce
Author-email: masonpierce@trainloop.ai
Requires-Python: >=3.9,<4.0
Classifier: Programming Language :: Python :: 3
Classifier: Programming Language :: Python :: 3.9
Classifier: Programming Language :: Python :: 3.10
Classifier: Programming Language :: Python :: 3.11
Classifier: Programming Language :: Python :: 3.12
Classifier: Programming Language :: Python :: 3.13
Requires-Dist: click (>=8.1.0,<9.0.0)
Requires-Dist: fsspec (>=2023.1.0)
Requires-Dist: litellm (>=1.72.0,<2.0.0)
Requires-Dist: packaging (>=23.0,<24.0)
Requires-Dist: pyyaml (>=6.0,<7.0)
Requires-Dist: tomli (>=2.0,<3.0)
